ndfind/__init__.py
ndfind/main.cpython-311-darwin.so
ndfind-0.4.1.dist-info/RECORD
ndfind-0.4.1.dist-info/WHEEL
ndfind-0.4.1.dist-info/top_level.txt
ndfind-0.4.1.dist-info/METADATA
